invoicepy/__init__.py
invoicepy/cli/__init__.py
invoicepy/cli/commands.py
invoicepy/cli/helpers.py
invoicepy/cli/main.py
invoicepy/config/__init__.py
invoicepy/config/sample_config.json
invoicepy/const.py
invoicepy/models.py
invoicepy/render.py
invoicepy/schema/config.json
invoicepy/schema/invoice.json
invoicepy/templates/dollar.png
invoicepy/templates/simple.html
invoicepy/templates/simple_lt.html
invoicepy/utils.py
invoicepy-0.1.2.dist-info/entry_points.txt
invoicepy-0.1.2.dist-info/LICENSE
invoicepy-0.1.2.dist-info/WHEEL
invoicepy-0.1.2.dist-info/METADATA
invoicepy-0.1.2.dist-info/RECORD
