Metadata-Version: 2.1
Name: invoicepy
Version: 0.1.2
Summary: invoicepy is a simple cli tool for generating and storing invoices.
Home-page: https://github.com/adamwojt/invoicepy
License: MIT
Keywords: invoicepy,invoice,cli,python,finance,tools
Author: Adam W.
Author-email: adam1edinburgh@gmail.com
Requires-Python: >=3.6,<4.0
Classifier: Development Status :: 3 - Alpha
Classifier: Intended Audience :: Developers
Classifier: Intended Audience :: End Users/Desktop
Classifier: Intended Audience :: Financial and Insurance Industry
Classifier: License :: OSI Approved :: MIT License
Classifier: Natural Language :: English
Classifier: Programming Language :: Python
Classifier: Programming Language :: Python :: 3
Classifier: Programming Language :: Python :: 3.6
Classifier: Programming Language :: Python :: 3.7
Classifier: Programming Language :: Python :: 3.8
Classifier: Programming Language :: Python :: 3.9
Classifier: Programming Language :: Python :: Implementation :: CPython
Classifier: Programming Language :: Python :: Implementation :: PyPy
Classifier: Topic :: Office/Business :: Financial
Classifier: Topic :: Office/Business :: Financial :: Accounting
Requires-Dist: Click (>=7.0,<8.0)
Requires-Dist: Jinja2 (>=3.0.0,<4.0.0)
Requires-Dist: pydantic[email] (>=1.8.0,<2.0.0)
Requires-Dist: weasyprint (>=53.0,<54.0)
Project-URL: Bug Tracker, https://github.com/adamwojt/invoicepy/issues
Project-URL: Documentation, https://github.com/adamwojt/invoicepy/README.md
Project-URL: Repository, https://github.com/adamwojt/invoicepy
Project-URL: Source, https://github.com/adamwojt/invoicepy
